rubu/temas.py
rubu-1.0.8.dist-info/LICENSE.txt
rubu-1.0.8.dist-info/METADATA
rubu-1.0.8.dist-info/WHEEL
rubu-1.0.8.dist-info/top_level.txt
rubu-1.0.8.dist-info/RECORD
