Metadata-Version: 2.1
Name: rubu
Version: 1.0.8
Summary: Temas Socket API for controlling and communicating with Temas devices
Author-email: Muhammed <info@rubu-tech.de>
License: MIT License
Keywords: temas,hardware-control,socket
Classifier: Programming Language :: Python :: 3
Classifier: Operating System :: OS Independent
Requires-Python: >=3.8
License-File: LICENSE.txt
